ajc27_freemocap_blender_addon/__init__.py
ajc27_freemocap_blender_addon/main.py
ajc27_freemocap_blender_addon/.idea/.gitignore
ajc27_freemocap_blender_addon/.idea/ajc27_freemocap_blender_addon.iml
ajc27_freemocap_blender_addon/.idea/misc.xml
ajc27_freemocap_blender_addon/.idea/modules.xml
ajc27_freemocap_blender_addon/.idea/vcs.xml
ajc27_freemocap_blender_addon/.idea/inspectionProfiles/profiles_settings.xml
ajc27_freemocap_blender_addon/assets/body_mesh.ply
ajc27_freemocap_blender_addon/assets/charuco_board.png
ajc27_freemocap_blender_addon/assets/freemocap_logo_white_outline.png
ajc27_freemocap_blender_addon/assets/skelly_full_mesh_20k_faces.blend
ajc27_freemocap_blender_addon/assets/skelly_lowpoly_mesh.fbx
ajc27_freemocap_blender_addon/assets/video_composite_background.png
ajc27_freemocap_blender_addon/assets/skelly_bones/Skelly_f_index.01.L.fbx
ajc27_freemocap_blender_addon/assets/skelly_bones/Skelly_f_index.01.R.fbx
ajc27_freemocap_blender_addon/assets/skelly_bones/Skelly_f_index.02.L.fbx
ajc27_freemocap_blender_addon/assets/skelly_bones/Skelly_f_index.02.R.fbx
ajc27_freemocap_blender_addon/assets/skelly_bones/Skelly_f_index.03.L.fbx
ajc27_freemocap_blender_addon/assets/skelly_bones/Skelly_f_index.03.R.fbx
ajc27_freemocap_blender_addon/assets/skelly_bones/Skelly_f_middle.01.L.fbx
ajc27_freemocap_blender_addon/assets/skelly_bones/Skelly_f_middle.01.R.fbx
ajc27_freemocap_blender_addon/assets/skelly_bones/Skelly_f_middle.02.L.fbx
ajc27_freemocap_blender_addon/assets/skelly_bones/Skelly_f_middle.02.R.fbx
ajc27_freemocap_blender_addon/assets/skelly_bones/Skelly_f_middle.03.L.fbx
ajc27_freemocap_blender_addon/assets/skelly_bones/Skelly_f_middle.03.R.fbx
ajc27_freemocap_blender_addon/assets/skelly_bones/Skelly_f_pinky.01.L.fbx
ajc27_freemocap_blender_addon/assets/skelly_bones/Skelly_f_pinky.01.R.fbx
ajc27_freemocap_blender_addon/assets/skelly_bones/Skelly_f_pinky.02.L.fbx
ajc27_freemocap_blender_addon/assets/skelly_bones/Skelly_f_pinky.02.R.fbx
ajc27_freemocap_blender_addon-2025.11.1038.dist-info/licenses/LICENSE
ajc27_freemocap_blender_addon-2025.11.1038.dist-info/WHEEL
ajc27_freemocap_blender_addon-2025.11.1038.dist-info/METADATA
ajc27_freemocap_blender_addon-2025.11.1038.dist-info/RECORD
