Metadata-Version: 2.4
Name: ajc27_freemocap_blender_addon
Version: 2025.11.1038
Summary: A Blender add-on for loading and visualizing motion capture data recorded with the FreeMoCap software (https://freemocap.org)
Author-email: Skelly FreeMoCap <info@freemocap.org>
Requires-Python: >=3.10,<3.13
License-File: LICENSE
Project-URL: Documentation, https://freemocap.github.io/documentation/
Project-URL: Github, https://github.com/freemocap/freemocap_blender_addon
Project-URL: Homepage, https://freemocap.org
